dash_dndkit/DragContext.py
dash_dndkit/Draggable.py
dash_dndkit/DraggableCard.py
dash_dndkit/DropContainer.py
dash_dndkit/__init__.py
dash_dndkit/_imports_.py
dash_dndkit-0.0.3.dist-info/LICENSE
dash_dndkit-0.0.3.dist-info/METADATA
dash_dndkit-0.0.3.dist-info/WHEEL
dash_dndkit-0.0.3.dist-info/top_level.txt
dash_dndkit-0.0.3.dist-info/RECORD
