Metadata-Version: 2.1
Name: dash-dndkit
Version: 0.0.3
Summary: Plotly Dash drag and drop support based on dnd-kit
Home-page: https://github.com/LuanAdemi/dash-dndkit
Author: Luan Ademi <luan.ademi@student.kit.edu>
Author-email: luan.ademi@student.kit.edu
License: MIT
Classifier: Framework :: Dash
Classifier: Framework :: Flask
License-File: LICENSE
